cloudmedia/__init__.py
cloudmedia/admin.py
cloudmedia/apps.py
cloudmedia/models.py
cloudmedia/tests.py
cloudmedia/views.py
cloudmedia/locale/zh_hans/LC_MESSAGES/django.mo
cloudmedia/locale/zh_hans/LC_MESSAGES/django.po
cloudmedia/migrations/0001_initial.py
cloudmedia/migrations/__init__.py
cloudmedia/storage/__init__.py
cloudmedia/storage/cos.py
cloudmedia/storage/obs.py
cloudmedia/storage/oss.py
django_cloudmedia-1.0.2.dist-info/LICENSE
django_cloudmedia-1.0.2.dist-info/METADATA
django_cloudmedia-1.0.2.dist-info/WHEEL
django_cloudmedia-1.0.2.dist-info/top_level.txt
django_cloudmedia-1.0.2.dist-info/RECORD
