Metadata-Version: 2.1
Name: django-cloudmedia
Version: 1.0.2
Summary: Cloud media manager for Django, support for aliyun OSS, Tencent COS, Huawei OBS
Home-page: https://github.com/twn39/django-cloudmedia
Author: twn39
Author-email: twn39@163.com
License: MIT
Platform: UNKNOWN
Classifier: Environment :: Web Environment
Classifier: Framework :: Django
Classifier: Framework :: Django :: 3.0
Classifier: Framework :: Django :: 3.1
Classifier: Framework :: Django :: 3.2
Classifier: Intended Audience :: Developers
Classifier: License :: OSI Approved :: BSD License
Classifier: Operating System :: OS Independent
Classifier: Programming Language :: Python
Classifier: Programming Language :: Python :: 3
Classifier: Programming Language :: Python :: 3 :: Only
Classifier: Programming Language :: Python :: 3.6
Classifier: Programming Language :: Python :: 3.7
Classifier: Programming Language :: Python :: 3.8
Classifier: Topic :: Internet :: WWW/HTTP
Classifier: Topic :: Internet :: WWW/HTTP :: Dynamic Content
Requires-Python: >=3.6
License-File: LICENSE
Requires-Dist: Django (>=3.0)
Requires-Dist: oss2 (>=2.15)
Requires-Dist: cos-python-sdk-v5 (>=1.9.10)
Requires-Dist: esdk-obs-python (>=3.21)
Requires-Dist: Pillow (>=8.4)
